{
    "os": "macOS-14.5-arm64-arm-64bit",
    "python": "3.10.15",
    "heartbeatAt": "2024-10-30T18:53:37.778759",
    "startedAt": "2024-10-30T18:53:29.061256",
    "docker": null,
    "cuda": null,
    "args": [],
    "state": "running",
    "program": "eda.ipynb",
    "codePathLocal": "eda.ipynb",
    "root": "/Users/jerry/Project-Build-an-ML-Pipeline-Starter",
    "git": {
        "remote": "https://github.com/Jerryd111/Project-Build-an-ML-Pipeline-Starter.git",
        "commit": "0936351046db1e8e7587aa16f516b26a9374b3da"
    },
    "email": "gdonofr@wgu.edu",
    "host": "MacBook-Pro-2.attlocal.net",
    "username": "jerry",
    "executable": "/Users/jerry/miniconda3/envs/nyc_airbnb_dev/bin/python",
    "cpu_count": 12,
    "cpu_count_logical": 12,
    "cpu_freq": {
        "current": 4056,
        "min": 696,
        "max": 4056
    },
    "cpu_freq_per_core": [
        {
            "current": 4056,
            "min": 696,
            "max": 4056
        }
    ],
    "disk": {
        "/": {
            "total": 460.4317207336426,
            "used": 167.85394287109375
        }
    },
    "gpuapple": {
        "type": "arm",
        "vendor": "Apple"
    },
    "memory": {
        "total": 36.0
    }
}
